fivetran_mcp/__init__.py
fivetran_mcp/fivetran_api.py
fivetran_mcp/server.py
fivetran_mcp-0.3.0.dist-info/METADATA
fivetran_mcp-0.3.0.dist-info/WHEEL
fivetran_mcp-0.3.0.dist-info/entry_points.txt
fivetran_mcp-0.3.0.dist-info/licenses/LICENSE
fivetran_mcp-0.3.0.dist-info/RECORD
