Metadata-Version: 2.4
Name: fivetran-mcp
Version: 0.3.0
Summary: MCP server for Fivetran API - manage syncs, check status, and control connections
Project-URL: Homepage, https://github.com/YimingYAN/fivetran-mcp
Project-URL: Repository, https://github.com/YimingYAN/fivetran-mcp
Project-URL: Issues, https://github.com/YimingYAN/fivetran-mcp/issues
Author: Yiming Yan
License-Expression: MIT
License-File: LICENSE
Keywords: data-engineering,etl,fivetran,mcp,model-context-protocol
Classifier: Development Status :: 4 - Beta
Classifier: Intended Audience :: Developers
Classifier: License :: OSI Approved :: MIT License
Classifier: Programming Language :: Python :: 3
Classifier: Programming Language :: Python :: 3.10
Classifier: Programming Language :: Python :: 3.11
Classifier: Programming Language :: Python :: 3.12
Classifier: Topic :: Software Development :: Libraries :: Python Modules
Requires-Python: >=3.10
Requires-Dist: fastmcp>=2.0.0
Requires-Dist: httpx>=0.28.0
